{
    "m_Version": 4,
    "m_FileName": "Ammo_Boxes",
    "CategoryID": 2,
    "DisplayName": "#STR_EXPANSION_MARKET_CATEGORY_AMMOBOXES",
    "Items": [
        {
            "ClassName": "ammobox_00buck_10rnd",
            "MaxPriceThreshold": 100,
            "MinPriceThreshold": 50,
            "MaxStockThreshold": 500,
            "MinStockThreshold": 1,
            "PurchaseType": 0,
            "SpawnAttachments": []
        },
        {
            "ClassName": "ammobox_12gaslug_10rnd",
            "MaxPriceThreshold": 100,
            "MinPriceThreshold": 50,
            "MaxStockThreshold": 500,
            "MinStockThreshold": 1,
            "PurchaseType": 0,
            "SpawnAttachments": []
        },
        {
            "ClassName": "ammobox_12garubberslug_10rnd",
            "MaxPriceThreshold": 75,
            "MinPriceThreshold": 40,
            "MaxStockThreshold": 500,
            "MinStockThreshold": 1,
            "PurchaseType": 0,
            "SpawnAttachments": []
        },
        {
            "ClassName": "ammobox_22_50rnd",
            "MaxPriceThreshold": 200,
            "MinPriceThreshold": 100,
            "MaxStockThreshold": 500,
            "MinStockThreshold": 1,
            "PurchaseType": 0,
            "SpawnAttachments": []
        },
        {
            "ClassName": "ammobox_308win_20rnd",
            "MaxPriceThreshold": 150,
            "MinPriceThreshold": 100,
            "MaxStockThreshold": 500,
            "MinStockThreshold": 1,
            "PurchaseType": 0,
            "SpawnAttachments": []
        },
        {
            "ClassName": "ammobox_308wintracer_20rnd",
            "MaxPriceThreshold": 175,
            "MinPriceThreshold": 125,
            "MaxStockThreshold": 500,
            "MinStockThreshold": 1,
            "PurchaseType": 0,
            "SpawnAttachments": []
        },
        {
            "ClassName": "ammobox_357_20rnd",
            "MaxPriceThreshold": 250,
            "MinPriceThreshold": 125,
            "MaxStockThreshold": 500,
            "MinStockThreshold": 1,
            "PurchaseType": 0,
            "SpawnAttachments": []
        },
        {
            "ClassName": "ammobox_380_35rnd",
            "MaxPriceThreshold": 350,
            "MinPriceThreshold": 175,
            "MaxStockThreshold": 500,
            "MinStockThreshold": 1,
            "PurchaseType": 0,
            "SpawnAttachments": []
        },
        {
            "ClassName": "ammobox_45acp_25rnd",
            "MaxPriceThreshold": 250,
            "MinPriceThreshold": 125,
            "MaxStockThreshold": 500,
            "MinStockThreshold": 1,
            "PurchaseType": 0,
            "SpawnAttachments": []
        },
        {
            "ClassName": "ammobox_545x39_20rnd",
            "MaxPriceThreshold": 200,
            "MinPriceThreshold": 100,
            "MaxStockThreshold": 500,
            "MinStockThreshold": 1,
            "PurchaseType": 0,
            "SpawnAttachments": []
        },
        {
            "ClassName": "ammobox_545x39tracer_20rnd",
            "MaxPriceThreshold": 200,
            "MinPriceThreshold": 100,
            "MaxStockThreshold": 500,
            "MinStockThreshold": 1,
            "PurchaseType": 0,
            "SpawnAttachments": []
        },
        {
            "ClassName": "ammobox_556x45_20rnd",
            "MaxPriceThreshold": 150,
            "MinPriceThreshold": 100,
            "MaxStockThreshold": 500,
            "MinStockThreshold": 1,
            "PurchaseType": 0,
            "SpawnAttachments": []
        },
        {
            "ClassName": "ammobox_556x45tracer_20rnd",
            "MaxPriceThreshold": 150,
            "MinPriceThreshold": 100,
            "MaxStockThreshold": 500,
            "MinStockThreshold": 1,
            "PurchaseType": 0,
            "SpawnAttachments": []
        },
        {
            "ClassName": "ammobox_762x39_20rnd",
            "MaxPriceThreshold": 200,
            "MinPriceThreshold": 100,
            "MaxStockThreshold": 500,
            "MinStockThreshold": 1,
            "PurchaseType": 0,
            "SpawnAttachments": []
        },
        {
            "ClassName": "ammobox_762x39tracer_20rnd",
            "MaxPriceThreshold": 200,
            "MinPriceThreshold": 100,
            "MaxStockThreshold": 500,
            "MinStockThreshold": 1,
            "PurchaseType": 0,
            "SpawnAttachments": []
        },
        {
            "ClassName": "ammobox_762x54_20rnd",
            "MaxPriceThreshold": 150,
            "MinPriceThreshold": 100,
            "MaxStockThreshold": 500,
            "MinStockThreshold": 1,
            "PurchaseType": 0,
            "SpawnAttachments": []
        },
        {
            "ClassName": "ammobox_762x54tracer_20rnd",
            "MaxPriceThreshold": 150,
            "MinPriceThreshold": 100,
            "MaxStockThreshold": 500,
            "MinStockThreshold": 1,
            "PurchaseType": 0,
            "SpawnAttachments": []
        },
        {
            "ClassName": "ammobox_9x19_25rnd",
            "MaxPriceThreshold": 250,
            "MinPriceThreshold": 120,
            "MaxStockThreshold": 500,
            "MinStockThreshold": 1,
            "PurchaseType": 0,
            "SpawnAttachments": []
        },
        {
            "ClassName": "ammobox_9x39ap_20rnd",
            "MaxPriceThreshold": 200,
            "MinPriceThreshold": 100,
            "MaxStockThreshold": 500,
            "MinStockThreshold": 1,
            "PurchaseType": 0,
            "SpawnAttachments": []
        },
        {
            "ClassName": "ammobox_9x39_20rnd",
            "MaxPriceThreshold": 200,
            "MinPriceThreshold": 100,
            "MaxStockThreshold": 500,
            "MinStockThreshold": 1,
            "PurchaseType": 0,
            "SpawnAttachments": []
        },
        {
            "ClassName": "ammobox_expansion_46x30_25rnd",
            "MaxPriceThreshold": 200,
            "MinPriceThreshold": 100,
            "MaxStockThreshold": 500,
            "MinStockThreshold": 1,
            "PurchaseType": 0,
            "SpawnAttachments": []
        },
        {
            "ClassName": "ammobox_expansion_338_15rnd",
            "MaxPriceThreshold": 200,
            "MinPriceThreshold": 100,
            "MaxStockThreshold": 500,
            "MinStockThreshold": 1,
            "PurchaseType": 0,
            "SpawnAttachments": []
        },
        {
            "ClassName": "expansion_ammobox_8mm_15rnd",
            "MaxPriceThreshold": 200,
            "MinPriceThreshold": 100,
            "MaxStockThreshold": 500,
            "MinStockThreshold": 1,
            "PurchaseType": 0,
            "SpawnAttachments": []
        }
    ]
}